{
  "pageid": 1338,
  "ns": 0,
  "title": "Brainworm Neuron",
  "fullurl": "https://supersnail.wiki.gg/wiki/Brainworm_Neuron",
  "touched": "2025-06-21T12:30:29Z",
  "length": 409,
  "lastrevid": 36803,
  "revision": {
    "revid": 36803,
    "parentid": 35438,
    "timestamp": "2025-06-21T12:30:29Z",
    "sha1": "062ac9b5d2d9829f0df738cf30383d5f7ef0bc23",
    "size": 409
  },
  "categories": [
    "Blue Relics",
    "Relics"
  ],
  "likely_item_page": true,
  "infoboxes": [],
  "wikitext_path": "wikitext/Brainworm_Neuron.wiki",
  "markdown_path": "markdown/Brainworm_Neuron.md"
}