{
  "pageid": 1022,
  "ns": 0,
  "title": "Exploration",
  "fullurl": "https://supersnail.wiki.gg/wiki/Exploration",
  "touched": "2023-07-25T05:59:28Z",
  "length": 215,
  "lastrevid": 6371,
  "revision": {
    "revid": 6371,
    "parentid": 2119,
    "timestamp": "2023-07-25T05:59:28Z",
    "sha1": "888d18278ee9e6722e9b5462a5bbd9af017d623b",
    "size": 215
  },
  "categories": [],
  "likely_item_page": false,
  "infoboxes": [],
  "wikitext_path": "wikitext/Exploration.wiki",
  "markdown_path": "markdown/Exploration.md"
}