{
  "pageid": 9411,
  "ns": 0,
  "title": "Guard Chorister",
  "fullurl": "https://supersnail.wiki.gg/wiki/Guard_Chorister",
  "touched": "2025-06-20T16:02:14Z",
  "length": 204,
  "lastrevid": 36406,
  "revision": {
    "revid": 36406,
    "parentid": 0,
    "timestamp": "2025-06-20T16:02:14Z",
    "sha1": "dd8409a5654b0e1bbeea639c533bbefc30a21162",
    "size": 204
  },
  "categories": [
    "Blue Clones",
    "Clones"
  ],
  "likely_item_page": false,
  "infoboxes": [],
  "wikitext_path": "wikitext/Guard_Chorister.wiki",
  "markdown_path": "markdown/Guard_Chorister.md"
}