{
  "pageid": 9515,
  "ns": 0,
  "title": "Idol Boy",
  "fullurl": "https://supersnail.wiki.gg/wiki/Idol_Boy",
  "touched": "2025-06-20T16:04:32Z",
  "length": 287,
  "lastrevid": 36510,
  "revision": {
    "revid": 36510,
    "parentid": 0,
    "timestamp": "2025-06-20T16:04:32Z",
    "sha1": "92c0894a991e53467c16abaa2e91089a32cb7709",
    "size": 287
  },
  "categories": [
    "Clones",
    "Orange Clones"
  ],
  "likely_item_page": false,
  "infoboxes": [],
  "wikitext_path": "wikitext/Idol_Boy.wiki",
  "markdown_path": "markdown/Idol_Boy.md"
}