{
  "pageid": 9739,
  "ns": 0,
  "title": "Lucian Argentlily",
  "fullurl": "https://supersnail.wiki.gg/wiki/Lucian_Argentlily",
  "touched": "2025-06-20T16:49:49Z",
  "length": 305,
  "lastrevid": 36756,
  "revision": {
    "revid": 36756,
    "parentid": 0,
    "timestamp": "2025-06-20T16:49:42Z",
    "sha1": "79a8f06cdec45ff341598d5e07f304c42ab6fa99",
    "size": 305
  },
  "categories": [
    "Clones",
    "Red Clones"
  ],
  "likely_item_page": false,
  "infoboxes": [],
  "wikitext_path": "wikitext/Lucian_Argentlily.wiki",
  "markdown_path": "markdown/Lucian_Argentlily.md"
}