{
  "pageid": 3028,
  "ns": 0,
  "title": "Luxury Shell III",
  "fullurl": "https://supersnail.wiki.gg/wiki/Luxury_Shell_III",
  "touched": "2025-02-06T19:34:32Z",
  "length": 327,
  "lastrevid": 32584,
  "revision": {
    "revid": 32584,
    "parentid": 12943,
    "timestamp": "2024-12-28T15:24:21Z",
    "sha1": "82405967589e9e8f248d12a8a434c68546e5e24b",
    "size": 327
  },
  "categories": [
    "ATK Boost",
    "DEF Boost",
    "FAME Shells",
    "Shells",
    "Water DMG Boost",
    "Yamato",
    "Zombie Form"
  ],
  "likely_item_page": false,
  "infoboxes": [],
  "wikitext_path": "wikitext/Luxury_Shell_III.wiki",
  "markdown_path": "markdown/Luxury_Shell_III.md"
}