{
  "pageid": 5435,
  "ns": 0,
  "title": "Midsummer Night's Dream",
  "fullurl": "https://supersnail.wiki.gg/wiki/Midsummer_Night%27s_Dream",
  "touched": "2025-02-06T19:34:32Z",
  "length": 648,
  "lastrevid": 20368,
  "revision": {
    "revid": 20368,
    "parentid": 20367,
    "timestamp": "2023-12-08T17:48:20Z",
    "sha1": "f97a8ae61e851f17cda5ef56ae78908da6db9017",
    "size": 648
  },
  "categories": [
    "DEF Boost",
    "FTH Shells",
    "Missing Info",
    "Shells"
  ],
  "likely_item_page": false,
  "infoboxes": [],
  "wikitext_path": "wikitext/Midsummer_Night_s_Dream.wiki",
  "markdown_path": "markdown/Midsummer_Night_s_Dream.md"
}