{
  "pageid": 2481,
  "ns": 0,
  "title": "Must-Not-Name",
  "fullurl": "https://supersnail.wiki.gg/wiki/Must-Not-Name",
  "touched": "2025-03-05T08:07:01Z",
  "length": 9244,
  "lastrevid": 30458,
  "revision": {
    "revid": 30458,
    "parentid": 28244,
    "timestamp": "2024-10-23T12:45:08Z",
    "sha1": "76111ff572760685fb12c1e180245b9230baca91",
    "size": 9244
  },
  "categories": [
    "Partners"
  ],
  "likely_item_page": false,
  "infoboxes": [],
  "wikitext_path": "wikitext/Must-Not-Name.wiki",
  "markdown_path": "markdown/Must-Not-Name.md"
}