{
  "pageid": 9172,
  "ns": 0,
  "title": "Quantum Silicon Neuron",
  "fullurl": "https://supersnail.wiki.gg/wiki/Quantum_Silicon_Neuron",
  "touched": "2025-06-21T12:35:03Z",
  "length": 617,
  "lastrevid": 36868,
  "revision": {
    "revid": 36868,
    "parentid": 35525,
    "timestamp": "2025-06-21T12:35:03Z",
    "sha1": "fdc0dbc57aa1e05162be9898c629c8130e80da29",
    "size": 617
  },
  "categories": [
    "Orange Relics",
    "Relics"
  ],
  "likely_item_page": true,
  "infoboxes": [],
  "wikitext_path": "wikitext/Quantum_Silicon_Neuron.wiki",
  "markdown_path": "markdown/Quantum_Silicon_Neuron.md"
}