{
  "pageid": 450,
  "ns": 0,
  "title": "Super Nerve Fiber",
  "fullurl": "https://supersnail.wiki.gg/wiki/Super_Nerve_Fiber",
  "touched": "2025-06-21T12:34:14Z",
  "length": 578,
  "lastrevid": 36836,
  "revision": {
    "revid": 36836,
    "parentid": 35476,
    "timestamp": "2025-06-21T12:34:14Z",
    "sha1": "6a0a1b9413702b4e47ce367f6bb11021796257fb",
    "size": 578
  },
  "categories": [
    "Purple Relics",
    "Relics"
  ],
  "likely_item_page": true,
  "infoboxes": [],
  "wikitext_path": "wikitext/Super_Nerve_Fiber.wiki",
  "markdown_path": "markdown/Super_Nerve_Fiber.md"
}